__main__.py
striem_configure/__init__.py
striem_configure/app.py
striem_configure/common.py
striem_configure/inputs.py
striem_configure/save.py
striem_configure/util.py
striem_configure/includes/vrl/aws/cloudtrail/remap.vrl
striem_configure/includes/vrl/github/audit/remap.vrl
striem_configure/includes/vrl/google.cloud/audit/remap.vrl
striem_configure/includes/vrl/okta/remap.vrl
striem_configure/includes/vrl/wiz/issue/remap.vrl
striem_configure/sources/__init__.py
striem_configure/sources/_source.py
striem_configure/sources/aws_cloudtrail.py
striem_configure/sources/gcp.py
striem_configure/sources/github_audit.py
striem_configure/sources/okta.py
striem_configure/static/docker-compose.yaml
striem_configure/static/vector/_striem.yaml
striem_configure/template/aws_cloudtrail.yaml
striem_configure/template/gcp.yaml
striem_configure/template/github_audit.yaml
striem_configure/template/okta.yaml
striem_configure-0.0.1.dist-info/licenses/LICENSE
striem_configure-0.0.1.dist-info/METADATA
striem_configure-0.0.1.dist-info/WHEEL
striem_configure-0.0.1.dist-info/entry_points.txt
striem_configure-0.0.1.dist-info/top_level.txt
striem_configure-0.0.1.dist-info/RECORD
