Metadata-Version: 2.4
Name: striem_configure
Version: 0.0.1
Summary: Configuration utility for the StrIEM open-source SIEM
Author-email: "Crowdalert, Inc" <hello@crowdalert.com>
License-Expression: MPL-2.0
Project-URL: Homepage, https://github.com/crowdalert/striem-configure
Project-URL: Issues, https://github.com/crowdalert/striem-configure
Classifier: Programming Language :: Python :: 3
Classifier: Operating System :: OS Independent
Requires-Python: >=3.10
License-File: LICENSE
Requires-Dist: prompt_toolkit~=3.0
Requires-Dist: pyyaml~=6.0
Requires-Dist: requests~=2.32
Dynamic: license-file
